text_parser_generator/__init__.py
text_parser_generator/__main__.py
text_parser_generator/cast.py
text_parser_generator/generator.py
text_parser_generator/model.py
text_parser_generator/parser.py
text_parser_generator/templates/class.j2
text_parser_generator/templates/file.j2
text_parser_generator/templates/instance.j2
text_parser_generator/templates/step.j2
text_parser_generator/templates/step_action.j2
text_parser_generator/templates/step_action_contents.j2
text_parser_generator/templates/step_action_str.j2
text_parser_generator/templates/step_action_substream.j2
text_parser_generator/templates/step_action_subtype.j2
text_parser_generator/templates/step_cast.j2
text_parser_generator/templates/step_defaults.j2
text_parser_generator/templates/step_lookup.j2
text_parser_generator/templates/step_repeat.j2
text_parser_generator-1.0.0.dist-info/METADATA
text_parser_generator-1.0.0.dist-info/WHEEL
text_parser_generator-1.0.0.dist-info/entry_points.txt
text_parser_generator-1.0.0.dist-info/top_level.txt
text_parser_generator-1.0.0.dist-info/RECORD
